{"size": 4, "name": "acpi_add_pm_notifier", "sourcefile": "N/A", "children": [{"size": 1, "name": "acpi_dev_pm_attach", "sourcefile": "N/A", "children": [{"size": 1, "name": "dev_pm_domain_attach", "sourcefile": "N/A", "children": [{"size": 1, "name": "platform_drv_probe", "sourcefile": "N/A", "children": []}, {"size": 1, "name": "i2c_device_probe", "sourcefile": "N/A", "children": []}, {"size": 1, "name": "sdio_bus_probe", "sourcefile": "N/A", "children": []}, {"size": 1, "name": "spi_drv_probe", "sourcefile": "N/A", "children": []}]}]}, {"size": 1, "name": "pci_acpi_add_bus_pm_notifier", "sourcefile": "N/A", "children": [{"size": 1, "name": "acpi_pci_root_add", "sourcefile": "N/A", "children": []}]}, {"size": 1, "name": "pci_acpi_setup", "sourcefile": "N/A", "children": []}, {"size": 1, "name": "pci_acpi_add_pm_notifier", "sourcefile": "N/A", "children": []}]}