{"size": 4, "name": "apic_is_x2apic_enabled", "sourcefile": "N/A", "children": [{"size": 1, "name": "setup_nox2apic", "sourcefile": "N/A", "children": []}, {"size": 1, "name": "check_x2apic", "sourcefile": "N/A", "children": [{"size": 1, "name": "setup_arch", "sourcefile": "N/A", "children": [{"size": 1, "name": "start_kernel", "sourcefile": "N/A", "children": [{"size": 1, "name": "x86_64_start_reservations", "sourcefile": "N/A", "children": [{"size": 1, "name": "xen_start_kernel", "sourcefile": "N/A", "children": []}, {"size": 1, "name": "initial_code", "sourcefile": "TODO", "children": []}, {"size": 1, "name": "x86_64_start_kernel", "sourcefile": "N/A", "children": []}]}]}]}]}, {"size": 1, "name": "enable_IR_x2apic", "sourcefile": "N/A", "children": [{"size": 1, "name": "default_setup_apic_routing", "sourcefile": "N/A", "children": [{"size": 1, "name": "native_smp_prepare_cpus", "sourcefile": "N/A", "children": [{"size": 1, "name": "xen_hvm_smp_prepare_cpus", "sourcefile": "N/A", "children": []}]}, {"size": 1, "name": "APIC_init_uniprocessor", "sourcefile": "N/A", "children": []}]}]}]}