{"size": 4, "name": "ata_xfer_mode2mask", "sourcefile": "N/A", "children": [{"size": 1, "name": "ata_do_set_mode", "sourcefile": "N/A", "children": [{"size": 1, "name": "ata_set_mode", "sourcefile": "N/A", "children": [{"size": 1, "name": "ata_eh_recover", "sourcefile": "N/A", "children": [{"size": 1, "name": "ata_do_eh", "sourcefile": "N/A", "children": [{"size": 1, "name": "ata_sff_error_handler", "sourcefile": "N/A", "children": [{"size": 1, "name": "ata_bmdma_error_handler", "sourcefile": "N/A", "children": []}]}, {"size": 1, "name": "ata_std_error_handler", "sourcefile": "N/A", "children": []}]}, {"size": 1, "name": "sata_pmp_error_handler", "sourcefile": "N/A", "children": []}]}, {"size": 1, "name": "ata_bus_probe", "sourcefile": "N/A", "children": [{"size": 1, "name": "ata_port_probe", "sourcefile": "N/A", "children": [{"size": 1, "name": "async_port_probe", "sourcefile": "N/A", "children": []}, {"size": 1, "name": "ata_sas_sync_probe", "sourcefile": "N/A", "children": []}]}]}]}]}, {"size": 1, "name": "generic_set_mode", "sourcefile": "N/A", "children": []}, {"size": 1, "name": "ata_acpi_gtm_xfermask", "sourcefile": "N/A", "children": [{"size": 1, "name": "ata_acpi_cbl_80wire", "sourcefile": "N/A", "children": []}]}]}