{"size": 6, "name": "convert_from_fxsr", "sourcefile": "N/A", "children": [{"size": 1, "name": "fpregs_set", "sourcefile": "N/A", "children": []}, {"size": 1, "name": "save_fsave_header", "sourcefile": "N/A", "children": [{"size": 1, "name": "copy_fpstate_to_sigframe", "sourcefile": "N/A", "children": [{"size": 1, "name": "do_signal", "sourcefile": "N/A", "children": [{"size": 1, "name": "do_notify_resume", "sourcefile": "N/A", "children": [{"size": 1, "name": "ret_from_intr", "sourcefile": "N/A", "children": []}, {"size": 1, "name": "int_signal", "sourcefile": "N/A", "children": []}, {"size": 1, "name": "entry_SYSCALL_64", "sourcefile": "N/A", "children": []}, {"size": 1, "name": "common_interrupt", "sourcefile": "N/A", "children": []}, {"size": 1, "name": "entry_SYSCALL_64_after_swapgs", "sourcefile": "N/A", "children": []}, {"size": 1, "name": "retint_signal", "sourcefile": "N/A", "children": []}]}]}]}]}, {"size": 1, "name": "fpregs_get", "sourcefile": "N/A", "children": [{"size": 1, "name": "dump_fpu", "sourcefile": "N/A", "children": []}]}]}